wildq/__init__.py
wildq/__main__.py
wildq/_wildq_version.py
wildq/cli.py
wildq/filetypes/__init__.py
wildq/filetypes/hcl_type.py
wildq/filetypes/ini_type.py
wildq/filetypes/json_type.py
wildq/filetypes/toml_type.py
wildq/filetypes/xml_type.py
wildq/filetypes/yaml_type.py
wildq-1.1.11.dist-info/entry_points.txt
wildq-1.1.11.dist-info/LICENSE
wildq-1.1.11.dist-info/WHEEL
wildq-1.1.11.dist-info/METADATA
wildq-1.1.11.dist-info/RECORD
