Metadata-Version: 2.1
Name: wildq
Version: 1.1.11
Summary: Command-line TOML/JSON/INI/YAML/XML processor using jq c bindings.
Home-page: https://github.com/ahmet2mir/wildq
License: Apache 2.0
Keywords: wildq,jq,yaml,json,toml,xml,ini,parser,shell,hcl,color,highlight
Author: Ahmet Demir
Author-email: me@ahmet2mir.eu
Requires-Python: >=3.6,<4.0
Classifier: Development Status :: 4 - Beta
Classifier: Environment :: Console
Classifier: Intended Audience :: Developers
Classifier: License :: OSI Approved :: Apache Software License
Classifier: License :: Other/Proprietary License
Classifier: Operating System :: OS Independent
Classifier: Programming Language :: Python
Classifier: Programming Language :: Python :: 3
Classifier: Programming Language :: Python :: 3 :: Only
Classifier: Programming Language :: Python :: 3.10
Classifier: Programming Language :: Python :: 3.6
Classifier: Programming Language :: Python :: 3.7
Classifier: Programming Language :: Python :: 3.8
Classifier: Programming Language :: Python :: 3.9
Classifier: Topic :: Software Development :: Build Tools
Classifier: Topic :: Software Development :: Libraries :: Python Modules
Requires-Dist: PyYAML (>=5.3.1,<6.0.0)
Requires-Dist: Pygments (>=2.7.2,<3.0.0)
Requires-Dist: click (>=7.1.2,<8.0.0)
Requires-Dist: jq (>=1.1.1,<2.0.0)
Requires-Dist: pyhcl (>=0.4.4,<0.5.0)
Requires-Dist: toml (>=0.10.1,<0.11.0)
Requires-Dist: xmltodict (>=0.12.0,<0.13.0)
Project-URL: Changelog, https://github.com/ahmet2mir/wildq/issues
Project-URL: Documentation, https://wildq.readthedocs.io/en/latest
Project-URL: Repository, https://github.com/ahmet2mir/wildq.git
